{
  "seo": {
    "slug": "jamaica-training-pay-guide-managing-workshop-development-compensation-2025",
    "title": "Jamaica Training Pay Guide: Managing Workshop & Development Compensation 2025",
    "description": "Expert guidance on managing training compensation, workshop pay, and development costs while staying compliant with Jamaican payroll regulations in 2025.",
    "keywords": [
      "PAYE Jamaica",
      "NIS rates Jamaica",
      "NHT contributions",
      "education tax Jamaica",
      "overtime rules Jamaica",
      "statutory deductions Jamaica",
      "payroll tax Jamaica",
      "employee benefits Jamaica",
      "training allowance Jamaica",
      "workshop compensation",
      "staff development costs",
      "payroll compliance Jamaica",
      "minimum wage Jamaica",
      "severance pay Jamaica",
      "employee training costs"
    ]
  },
  "image": "/og.jpg",
  "title": "Jamaica Training Pay Guide: Managing Workshop & Development Compensation 2025",
  "subtitle": "A Practical Guide for Payroll Managers and HR Professionals",
  "links": {
    "ctaInline": {
      "headline": "Need help with payroll compliance?",
      "text": "Get expert guidance on training compensation and statutory deductions"
    },
    "ctaBottom": {
      "headline": "Stay compliant with changing regulations",
      "text": "Book a consultation with our payroll specialists"
    }
  },
  "html": "<p>Training compensation is one of those areas where even experienced payroll managers can stumble. The rules aren't just about basic pay, they're wrapped up in <a href='https://payrolljamaica.com'>overtime rules jamaica</a> and various allowances that need careful handling. As we move into 2025, understanding these complexities becomes even more crucial for maintaining compliance and ensuring fair compensation.</p><h2>Understanding Training Pay Components</h2><p>When calculating training pay, you'll need to factor in both regular wages and any special allowances. The base calculation starts with the standard <a href='https://payrolljamaica.com'>income tax jamaica rates</a>, but there's more to consider. Training hours often extend beyond normal working hours, triggering overtime considerations. For 2025, organizations must carefully evaluate:</p><p><ul><li>Base training wages aligned with current minimum wage requirements</li><li>Differential pay for specialized training sessions</li><li>Evening and weekend training premiums</li><li>Professional certification allowances</li><li>Skill development bonuses</li><li>Remote training compensation structures</li></ul></p><h2>Workshop Compensation Guidelines</h2><p>Workshop pay requires special attention to <a href='https://payrolljamaica.com'>nht contributions</a> and other statutory deductions. Here's what you need to track:<ul><li>Regular working hours vs. training hours</li><li>Meal allowances during extended sessions</li><li>Transportation costs</li><li>Materials and equipment allowances</li><li>Technology stipends for virtual workshops</li><li>Facilitator and mentor premiums</li></ul></p><p>Workshop compensation has evolved significantly, particularly with the rise of hybrid learning environments. Organizations must now consider both in-person and virtual workshop expenses, including digital platform subscriptions and online material costs.</p><h2>Development Program Costs</h2><p>Staff development programs often involve complex compensation structures. You'll need to understand how <a href='https://payrolljamaica.com'>severance calculation jamaica</a> rules apply when training agreements include retention clauses. Consider these key aspects:</p><p><ul><li>Long-term development program investments</li><li>Performance-based training incentives</li><li>Cross-training compensation adjustments</li><li>Career progression bonuses</li><li>International training allowances</li><li>Professional membership reimbursements</li></ul></p><h2>Statutory Deductions for Training Pay</h2><p>Training pay isn't exempt from statutory deductions. Remember to account for:<ul><li>PAYE on training allowances</li><li>NIS contributions</li><li>NHT and Education Tax</li><li>Other applicable benefits</li></ul></p><p>The 2025 regulations introduce new considerations for digital training benefits and remote learning allowances. Ensure your payroll systems are updated to handle these modern components while maintaining compliance with traditional statutory requirements.</p><h2>Special Considerations for Extended Training</h2><p>For longer training programs, particularly those lasting several months, you'll need to consider <a href='https://payrolljamaica.com'>severance pay jamaica</a> implications and how they affect your overall compensation structure. Extended training programs may require:</p><p><ul><li>Prorated benefit calculations</li><li>Adjusted insurance coverage</li><li>Modified leave accrual rates</li><li>Special accommodation allowances</li><li>Progress-based compensation adjustments</li><li>Return-of-service agreements</li></ul></p><h2>Record-Keeping Requirements</h2><p>Maintain detailed records of:<ul><li>Training attendance logs</li><li>Overtime hours during training</li><li>Special allowances paid</li><li>Signed training agreements</li><li>Certification completion dates</li><li>Digital learning platform access logs</li><li>Virtual attendance verification</li><li>Assessment and evaluation records</li></ul></p><h2>Common Compliance Pitfalls</h2><p>Watch out for these frequent issues:<ul><li>Incorrect overtime calculations for after-hours training</li><li>Missing statutory deductions on training allowances</li><li>Improper documentation of training agreements</li><li>Inconsistent application of meal and transport allowances</li><li>Overlooked digital platform subscription benefits</li><li>Incomplete virtual training attendance records</li><li>Misclassified training-related expenses</li></ul></p><h2>2025 Updates and Changes</h2><p>Recent updates to consider:<ul><li>Revised minimum wage rates affecting training pay calculations</li><li>Updated NHT contribution rates</li><li>New requirements for training agreement documentation</li><li>Modified overtime rules for professional development activities</li><li>Digital learning allowance guidelines</li><li>Remote training compensation frameworks</li><li>International training program regulations</li></ul></p><h2>Planning Ahead</h2><p>Start preparing your 2025 training budget with these factors in mind:<ul><li>Increased statutory rates</li><li>New compliance requirements</li><li>Documentation updates</li><li>System adjustments for new calculations</li><li>Digital platform investments</li><li>Hybrid learning cost structures</li><li>Professional development tracking systems</li></ul></p><p>Remember, training pay isn't just about the numbers, it's about maintaining compliance while investing in your team's development. Keep your documentation current and your calculations precise. As we navigate the evolving landscape of professional development, staying ahead of regulatory changes and maintaining accurate records becomes increasingly important for organizational success.</p>",
  "timestamp": "2025-11-24T10:44:13"
}
