{
  "seo": {
    "slug": "jamaica-recruitment-to-payroll-2025-guide-to-onboarding-new-hires-compliantly",
    "title": "Jamaica Recruitment to Payroll: 2025 Guide to Onboarding New Hires Compliantly",
    "description": "Master the critical steps from offer letter to first payroll run in Jamaica, with practical compliance guidance for 2025's updated regulations.",
    "keywords": [
      "payroll in Jamaica",
      "PAYE Jamaica",
      "NIS contributions Jamaica",
      "NHT contributions",
      "statutory deductions Jamaica",
      "Jamaica labor laws",
      "employment contracts Jamaica",
      "onboarding process Jamaica",
      "payroll compliance Jamaica",
      "education tax Jamaica",
      "severance pay Jamaica",
      "overtime rules Jamaica",
      "NIS rates Jamaica",
      "payroll taxes Jamaica",
      "employee benefits Jamaica"
    ]
  },
  "image": "/og.jpg",
  "title": "Jamaica Recruitment to Payroll: 2025 Guide to Onboarding New Hires Compliantly",
  "subtitle": "",
  "links": {
    "ctaInline": {
      "headline": "Need help with payroll compliance?",
      "text": "Get a free consultation with our payroll specialists"
    },
    "ctaBottom": {
      "headline": "Stay compliant with changing regulations",
      "text": "Download our 2025 Jamaica Payroll Compliance Checklist"
    }
  },
  "html": "<p>Here's what most HR managers get wrong about onboarding in Jamaica: they treat the offer letter as the starting point. But in 2025's regulatory environment, your compliance work needs to start way before that first handshake. Let me walk you through what actually matters.</p><h2>Pre-Offer Documentation: The Foundation of Compliant Onboarding</h2><p>Before you even think about <a href='https://payrolljamaica.com' rel='nofollow noopener'>payroll compliance jamaica</a>, you need your documentation house in order. I'm talking about position-specific contracts that reflect current labor laws, TRN verification procedures, and NIS registration forms. The Ministry's been particularly strict about employment contract specifics lately (trust me, I've seen the audits).</p><p>Your offer package must include:</p><ul><li>Employment contract with specific role duties</li><li>Statutory benefits documentation</li><li>Current year <a href='https://payrolljamaica.com' rel='nofollow noopener'>tax tables jamaica 2025</a> acknowledgment</li><li>NHT and NIS registration forms</li><li>Company-specific policies (especially regarding overtime and leave)</li></ul><h2>Setting Up Payroll: The Technical Details That Matter</h2><p>Once you've got signed documents, you've got 48 hours to register your new hire for <a href='https://payrolljamaica.com' rel='nofollow noopener'>jamaica payroll</a> deductions. Here's your sequence:</p><ol><li>Register employee TRN with tax office (if not already active)</li><li>Set up statutory deductions in your payroll system</li><li>Configure <a href='https://payrolljamaica.com' rel='nofollow noopener'>income tax jamaica rates</a> based on declared allowances</li><li>Establish payment schedule and method</li></ol><p>Pro tip: Don't just copy last year's deduction settings. The NHT contribution cap changed in January 2025, and I'm still seeing companies using outdated rates.</p><h2>Understanding the New 2025 Statutory Deductions Framework</h2><p>The landscape of statutory deductions has evolved significantly for 2025. Here's what you absolutely must get right:</p><p>NIS Contributions:</p><ul><li>Employee contribution: 3% of gross salary (up to the new ceiling)</li><li>Employer contribution: 3.5% (with adjusted maximum contribution limits)</li><li>Special provisions for seasonal workers introduced in 2025</li></ul><p>NHT Deductions:</p><ul><li>Employee contribution: 2% of gross salary</li><li>Employer contribution: 3% of gross salary</li><li>New ceiling amounts effective January 2025</li><li>Modified refund process for first-time homeowners</li></ul><p>Education Tax:</p><ul><li>Employee rate: 2.25% of gross salary</li><li>Employer contribution: 3.5%</li><li>New exemptions for specific industries</li></ul><h2>Leave and Benefits Setup: Often Overlooked Details</h2><p>Your new hire's <a href='https://payrolljamaica.com' rel='nofollow noopener'>vacation leave jamaica</a> entitlement starts accruing from day one. Common mistakes I see:</p><ul><li>Not documenting the leave year start date</li><li>Forgetting to prorate first-year vacation days</li><li>Missing sick leave policy documentation</li><li>Unclear overtime calculation methods</li></ul><h2>Digital Compliance Requirements for 2025</h2><p>The Ministry of Labour has introduced new digital compliance requirements that you can't ignore:</p><ul><li>Electronic submission of employee records within 24 hours of hiring</li><li>Digital tracking of working hours and overtime</li><li>Real-time reporting capabilities for statutory deductions</li><li>Automated verification of TRN and NIS numbers</li></ul><h2>First Payroll Run: Critical Checkpoints</h2><p>Your first payroll run is your compliance test. Double-check these often-missed items:</p><ul><li>Correct tax bracket application (especially for mid-year starts)</li><li>NIS ceiling calculations</li><li>Education tax rates (they're not always automatic in payroll systems)</li><li>Proper overtime rate setup (1.5x for regular overtime, 2x for public holidays)</li></ul><h2>Compliance Monitoring: Your 90-Day Checklist</h2><p>Set calendar reminders for these critical checkpoints:</p><ul><li>30 days: Verify all statutory deductions are processing correctly</li><li>60 days: First monthly statutory filing review</li><li>90 days: Complete probation period documentation</li></ul><h2>Record Keeping Requirements for 2025</h2><p>The digital transformation of payroll compliance means new record-keeping requirements:</p><ul><li>Digital copies of all onboarding documents</li><li>Audit trail of payroll calculations</li><li>Electronic proof of statutory payments</li><li>Digital attendance and leave records</li><li>Automated backup of all payroll data</li></ul><p>Remember, your payroll system might be automated, but your compliance obligations aren't. Keep detailed records of every step, especially now that the Ministry's doing more frequent digital audits.</p><p>Looking ahead to 2025, we're seeing increased scrutiny on digital compliance records. Start building your documentation system now, not when the auditor calls. And please, don't wait until month-end to fix payroll setup issues, the retroactive calculations will give you a headache (I'm speaking from experience here).</p><h2>Common Pitfalls to Avoid</h2><p>After years of helping companies navigate Jamaica's payroll landscape, here are the most expensive mistakes I see:</p><ul><li>Misclassifying workers as contractors</li><li>Incorrect calculation of overtime rates</li><li>Late registration for statutory deductions</li><li>Improper record keeping of working hours</li><li>Miscalculation of final pay during termination</li></ul><p>Stay ahead of these issues by implementing robust systems and regular audits of your payroll processes. Your future self will thank you when the compliance auditors come knocking.</p>",
  "timestamp": "2025-11-20T15:25:30"
}
