{
  "seo": {
    "slug": "jamaica-cash-flow-gap-calculator-aligning-employee-pay-dates-with-revenue-2025",
    "title": "Jamaica Cash Flow Gap Calculator: Aligning Employee Pay Dates with Revenue 2025",
    "description": "Master your business cash flow by strategically timing payroll cycles with revenue patterns. Practical guidance for Jamaican employers in 2025.",
    "keywords": [
      "cash flow gap calculator",
      "payroll management Jamaica",
      "PAYE Jamaica",
      "NIS rates Jamaica",
      "NHT contributions",
      "education tax Jamaica",
      "employee pay schedule",
      "payroll cash flow",
      "statutory deductions Jamaica",
      "payroll frequency Jamaica",
      "labour laws Jamaica overtime",
      "payroll tax calculator",
      "cash flow forecasting payroll",
      "biweekly payroll Jamaica",
      "monthly payroll Jamaica"
    ]
  },
  "image": "/og.jpg",
  "title": "Jamaica Cash Flow Gap Calculator: Aligning Employee Pay Dates with Revenue 2025",
  "subtitle": "Strategic timing of payroll cycles to optimize business cash flow",
  "links": {
    "ctaInline": {
      "headline": "Need help optimizing your payroll schedule?",
      "text": "Book a consultation with our payroll specialists"
    },
    "ctaBottom": {
      "headline": "Ready to streamline your payroll timing?",
      "text": "Download our free cash flow gap calculator template"
    }
  },
  "html": "<p>I've seen countless Jamaican businesses struggle with cash flow simply because their payroll timing doesn't match their revenue patterns. It's a headache that's entirely preventable with the right planning tools and strategic approach to payment scheduling.</p><p>Here's what most advisors won't tell you: the standard end-of-month payroll cycle isn't always your best option. Your optimal pay schedule should align with when you actually collect revenue, not just tradition or what other businesses are doing. This insight alone has helped many of my clients transform their cash flow management.</p><h2>Understanding Your Cash Flow Pattern</h2><p>First, let's tackle the basics of <a href='https://payrolljamaica.com' rel='nofollow noopener'>jamaica payroll</a> timing. Map out when your major revenue hits your account. For retail, it's often daily. For professional services, maybe it's the 15th and 30th. Construction companies typically see large payments at project milestones. The key is to understand your unique revenue rhythm.</p><p>Your cash flow gap is the time between when you need to pay employees and when you typically receive revenue. The wider this gap, the more working capital you need to keep on hand. This gap can be particularly challenging for seasonal businesses or those with irregular income patterns.</p><h2>Calculating Your Optimal Pay Schedule</h2><p>Here's a practical way to determine your ideal payroll timing:</p><p>1. List your monthly revenue dates and amounts - Be thorough and include all revenue streams<br>2. Note your <a href='https://payrolljamaica.com' rel='nofollow noopener'>paye jamaica</a> and other statutory due dates<br>3. Calculate your total monthly payroll cost including <a href='https://payrolljamaica.com' rel='nofollow noopener'>nht rates jamaica</a> and <a href='https://payrolljamaica.com' rel='nofollow noopener'>education tax rates jamaica</a><br>4. Factor in your <a href='https://payrolljamaica.com' rel='nofollow noopener'>overtime rules jamaica</a> and variable pay patterns<br>5. Analyze seasonal fluctuations in both revenue and expenses<br>6. Consider your current cash reserves and access to credit</p><h2>Strategic Pay Date Options</h2><p>Consider these proven approaches, each with distinct advantages:</p><p>Weekly: Best for businesses with daily cash receipts. Provides better cash flow control but requires more administrative work. Ideal for retail and hospitality sectors.</p><p>Bi-weekly: Ideal for steady revenue streams. Offers a good balance between employee satisfaction and administrative efficiency. Popular in manufacturing and service industries.</p><p>Semi-monthly: Works well with consistent contract payments. Simplifies accounting as dates align with half-months. Common in professional services and government contracts.</p><p>Monthly: Suits businesses with large, predictable month-end receipts. Reduces administrative burden but requires larger cash reserves.</p><h2>Managing Statutory Deductions Timing</h2><p>Remember, your statutory payments (PAYE, NIS, NHT) are due by the 14th of the following month. Smart timing can give you an extra 2-4 weeks to manage these obligations. I've seen companies save thousands in overdraft fees just by adjusting their pay dates to better align with this deadline.</p><p>Consider these statutory payment optimization strategies:</p><p>1. Align deduction calculations with pay periods<br>2. Build a buffer period between payroll processing and statutory due dates<br>3. Use electronic filing systems to reduce processing time<br>4. Maintain separate accounts for statutory obligations</p><h2>Real-World Application</h2><p>Let's look at a practical example. A retail client of mine shifted from monthly to bi-weekly payroll after analyzing their daily sales patterns. Their cash flow gap dropped from 22 days to just 8 days, freeing up nearly $2M in working capital. This transformation allowed them to invest in inventory expansion and store renovations without taking on additional debt.</p><p>Another client in the service industry moved from month-end to semi-monthly payments, aligning with their client payment schedules. This reduced their reliance on overdraft facilities by 60% and improved employee satisfaction as staff received more frequent payments.</p><h2>Implementation Steps</h2><p>1. Run your numbers through a cash flow gap calculator<br>2. Consult with employees about potential schedule changes - clear communication is crucial<br>3. Update your payroll systems and statutory payment schedules<br>4. Maintain a 30-day cash buffer during the transition<br>5. Monitor and adjust based on actual results<br>6. Document all changes and their impacts<br>7. Review and optimize quarterly</p><h2>Common Pitfalls to Avoid</h2><p>Don't make these mistakes I've seen too often:</p><p>- Changing schedules without proper employee notice and buy-in<br>- Forgetting to adjust statutory payment timing<br>- Overlooking seasonal revenue fluctuations<br>- Failing to maintain adequate cash reserves during the transition<br>- Not considering the administrative impact on your payroll team<br>- Ignoring the need for system updates or modifications</p><h2>Looking Ahead: 2025 Considerations</h2><p>With the new minimum wage adjustments coming in 2025 and potential changes to statutory rates, now is the perfect time to reassess your payroll timing. Start with a three-month trial of your new schedule while maintaining adequate reserves for the transition.</p><p>Consider these upcoming factors:</p><p>- Projected minimum wage increases and their impact on cash flow<br>- Changes in statutory contribution rates<br>- Digital payment adoption trends<br>- Remote work implications on payroll processing<br>- New compliance requirements</p><p>Remember, the goal isn't just to pay on time, it's to optimize your entire cash flow cycle. A well-planned payroll schedule can be the difference between struggling with working capital and having cash available for growth opportunities. Take the time to analyze your options and implement changes thoughtfully - your bottom line will thank you.</p><p>Managing a hotel or tourism property? <a href=\"/payroll-jamaica-hotels\">Payroll Jamaica is built for Jamaica's hotel industry</a> — align your seasonal revenue cycles with payroll timing, manage service charge distributions, and keep statutory obligations on track without the cash flow stress.</p><p>Running a restaurant or food service business? <a href=\"/payroll-jamaica-restaurants\">Payroll Jamaica handles restaurant payroll in Jamaica</a> — from aligning weekly revenue with staff pay cycles to managing tip income and variable hours, purpose-built for Jamaica's food service sector.</p>",
  "timestamp": "2025-12-19T09:03:31"
}
